README.md
setup.py
flexes_lib/__init__.py
flexes_lib/async_job.py
flexes_lib/job.py
flexes_lib/utils.py
flexes_lib.egg-info/PKG-INFO
flexes_lib.egg-info/SOURCES.txt
flexes_lib.egg-info/dependency_links.txt
flexes_lib.egg-info/requires.txt
flexes_lib.egg-info/top_level.txt
flexes_lib/aws/__init__.py
flexes_lib/aws/ec2_utils.py
flexes_lib/aws/s3_utils.py
test/test_async_job.py
test/test_ec2_utils.py
test/test_job.py
test/test_s3_utils.py
test/test_utils.py