Metadata-Version: 2.1
Name: flexes-lib
Version: 0.1.1
Summary: Helper library for interacting with flexes
Home-page: UNKNOWN
Author: James Arnold
License: UNKNOWN
Platform: UNKNOWN
Classifier: Programming Language :: Python :: 3
Classifier: License :: OSI Approved :: BSD License
Classifier: Operating System :: OS Independent
Provides-Extra: dev
